ikemurami/__init__.py
ikemurami/main.py
ikemurami-0.0.2.dist-info/METADATA
ikemurami-0.0.2.dist-info/WHEEL
ikemurami-0.0.2.dist-info/licenses/LICENSE
ikemurami-0.0.2.dist-info/RECORD
