Metadata-Version: 2.4
Name: ikemurami
Version: 0.0.2
Summary: Defense against dependency confusion attacks
Project-URL: Homepage, https://github.com/IkeMurami/pypi-package
Project-URL: Issues, https://github.com/IkeMurami/pypi-package/issues
Author-email: Petrakov Oleg <petrakov.oleg@yandex.ru>
License-Expression: MIT
License-File: LICENSE
Classifier: Operating System :: OS Independent
Classifier: Programming Language :: Python :: 3
Requires-Python: >=3.9
